mopidytermart/__init__.py
mopidytermart/__main__.py
mopidytermart/mopidytermart.py
mopidytermart-0.1.dist-info/METADATA
mopidytermart-0.1.dist-info/WHEEL
mopidytermart-0.1.dist-info/entry_points.txt
mopidytermart-0.1.dist-info/top_level.txt
mopidytermart-0.1.dist-info/RECORD
